{"days": [{"day": "Sunday", "time": {"endTime": "8:35", "startTime": "8:20"}}, {"day": "Monday", "time": {"endTime": "9:00", "startTime": "8:45"}}, {"day": "Tuesday", "time": {"endTime": "8:45", "startTime": "8:35"}}, {"day": "Wednesday", "time": {"endTime": "7:05", "startTime": "6:35"}}, {"day": "Thursday", "time": {"endTime": "7:00", "startTime": "6:35"}}, {"day": "Friday", "time": {"endTime": "7:00", "startTime": "6:35"}}, {"day": "Saturday", "time": {"endTime": "10:10", "startTime": "9:30"}}]}